aiommgpio/RPiMMIO.py
aiommgpio/__init__.py
aiommgpio/constants.py
aiommgpio/example.py
aiommgpio-1.0.0.dist-info/METADATA
aiommgpio-1.0.0.dist-info/WHEEL
aiommgpio-1.0.0.dist-info/licenses/LICENSE
aiommgpio-1.0.0.dist-info/RECORD
