Metadata-Version: 2.1
Name: aiommgpio
Version: 1.0.0
Summary: MMAP based GPIO & PWM for Raspberry Pi
Project-URL: Homepage, https://github.com/whdgmawkd/aiommgpio
Author-email: Park Jongheum <parkjh0821@gmail.com>
License-File: LICENSE
Classifier: License :: OSI Approved :: GNU General Public License v3 (GPLv3)
Classifier: Operating System :: POSIX :: Linux
Classifier: Programming Language :: Python :: 3
Classifier: Topic :: System :: Hardware
Requires-Python: >=3.7
